{
  "project_info": {
    "project_number": "954839568658",
    "project_id": "attendace-management-system",
    "storage_bucket": "attendace-management-system.appspot.com"
  },
  "client": [
    {
      "client_info": {
        "mobilesdk_app_id": "1:954839568658:android:c53d13660fb1d5add263cb",
        "android_client_info": {
          "package_name": "com.example.attsys"
        }
      },
      "oauth_client": [
        {
          "client_id": "954839568658-si80s4cs89me733fitc3hb83lhkj3fe8.apps.googleusercontent.com",
          "client_type": 3
        }
      ],
      "api_key": [
        {
          "current_key": "AIzaSyBHfQVjKstm2y1n8DgQPCZh_nbIYPepmdA"
        }
      ],
      "services": {
        "appinvite_service": {
          "other_platform_oauth_client": [
            {
              "client_id": "954839568658-si80s4cs89me733fitc3hb83lhkj3fe8.apps.googleusercontent.com",
              "client_type": 3
            },
            {
              "client_id": "954839568658-hgsrfgaegr9tglgjk75cn3kjnsi3m47i.apps.googleusercontent.com",
              "client_type": 2,
              "ios_info": {
                "bundle_id": "com.example.attsys"
              }
            }
          ]
        }
      }
    }
  ],
  "configuration_version": "1"
}